deep_timeit.py
deep_timeit-1.1.1.dist-info/LICENSE
deep_timeit-1.1.1.dist-info/METADATA
deep_timeit-1.1.1.dist-info/WHEEL
deep_timeit-1.1.1.dist-info/top_level.txt
deep_timeit-1.1.1.dist-info/RECORD
