Metadata-Version: 2.1
Name: deep-timeit
Version: 1.1.1
Summary: A package that allows timing of each individual line of code in a function, and produces a colour-coded output
Author-email: Oliver Gibson <ojrgibson@perse.co.uk>
Project-URL: Homepage, https://github.com/Yetiowner/Deep-time-it
Project-URL: Bug Tracker, https://github.com/Yetiowner/Deep-time-it/issues
Classifier: Programming Language :: Python :: 3
Classifier: License :: OSI Approved :: MIT License
Classifier: Operating System :: OS Independent
Requires-Python: >=3.6
License-File: LICENSE
